tea/__init__.py
tea/homepage.py
teaDAO-0.1.dist-info/LICENSE
teaDAO-0.1.dist-info/METADATA
teaDAO-0.1.dist-info/WHEEL
teaDAO-0.1.dist-info/top_level.txt
teaDAO-0.1.dist-info/RECORD
