Metadata-Version: 2.1
Name: teaDAO
Version: 0.1
Summary: demo teaDAO project for personal
Author: old-hansen
License-File: LICENSE
